pyjsonassert/__init__.py
pyjsonassert/json_assert.py
pyjsonassert/matchers/StringMatcher.py
pyjsonassert/matchers/UuidMatcher.py
pyjsonassert/matchers/__init__.py
pyJsonAssert-0.3.0.dist-info/LICENSE
pyJsonAssert-0.3.0.dist-info/METADATA
pyJsonAssert-0.3.0.dist-info/WHEEL
pyJsonAssert-0.3.0.dist-info/top_level.txt
pyJsonAssert-0.3.0.dist-info/RECORD
