Metadata-Version: 2.1
Name: pyJsonAssert
Version: 0.3.0
Summary: Facilitates Json asserts in REST API testing
Home-page: https://github.com/javierseixas/pyJsonAssert
Author: Javier Seixas
Author-email: dev@javierseixas.com
License: MIT
Keywords: json,api,testing,assert,assertion,comparing
Platform: UNKNOWN
Classifier: Programming Language :: Python :: 2.7
Classifier: Programming Language :: Python :: 3.4
Classifier: Programming Language :: Python :: 3.5
Classifier: Programming Language :: Python :: 3.6
Classifier: Development Status :: 2 - Pre-Alpha
Classifier: License :: OSI Approved :: MIT License
Requires-Dist: jsondiff (>=1.1)
